odoo/addons/stock_landed_costs_analytic/README.rst
odoo/addons/stock_landed_costs_analytic/__init__.py
odoo/addons/stock_landed_costs_analytic/__manifest__.py
odoo/addons/stock_landed_costs_analytic/i18n/es.po
odoo/addons/stock_landed_costs_analytic/i18n/fr.po
odoo/addons/stock_landed_costs_analytic/i18n/it.po
odoo/addons/stock_landed_costs_analytic/i18n/stock_landed_costs_analytic.pot
odoo/addons/stock_landed_costs_analytic/models/__init__.py
odoo/addons/stock_landed_costs_analytic/models/stock_landed_cost_lines.py
odoo/addons/stock_landed_costs_analytic/models/stock_valuation_adjustment_lines.py
odoo/addons/stock_landed_costs_analytic/static/description/icon.png
odoo/addons/stock_landed_costs_analytic/tests/__init__.py
odoo/addons/stock_landed_costs_analytic/tests/test_stock_landed_costs_analytic.py
odoo/addons/stock_landed_costs_analytic/views/stock_landed_cost_lines.xml
odoo_addon_stock_landed_costs_analytic-18.0.1.0.1.2.dist-info/METADATA
odoo_addon_stock_landed_costs_analytic-18.0.1.0.1.2.dist-info/WHEEL
odoo_addon_stock_landed_costs_analytic-18.0.1.0.1.2.dist-info/top_level.txt
odoo_addon_stock_landed_costs_analytic-18.0.1.0.1.2.dist-info/RECORD
