Metadata-Version: 2.1
Name: odoo-addon-stock_landed_costs_analytic
Version: 18.0.1.0.1.2
Requires-Python: >=3.10
Requires-Dist: odoo==18.0.*
Summary: This module adds an analytic account and analytic tags on landed costs lines so that on landed costs validation account moves get analytic account and analytic tags values from landed costs lines.
Home-page: https://github.com/OCA/account-analytic
License: AGPL-3
Author: ACSONE SA/NV,Odoo Community Association (OCA)
Author-email: support@odoo-community.org
Classifier: Programming Language :: Python
Classifier: Framework :: Odoo
Classifier: Framework :: Odoo :: 18.0
Classifier: License :: OSI Approved :: GNU Affero General Public License v3
